comforticons/__init__.py
comforticons/__main__.py
comforticons/generators/__init__.py
comforticons/generators/base.py
comforticons/generators/image.py
comforticons/generators/text.py
comforticons/main.py
comforticons/preprocessors/__init__.py
comforticons/preprocessors/base.py
comforticons/preprocessors/hash.py
comforticons-0.1.0.dist-info/METADATA
comforticons-0.1.0.dist-info/WHEEL
comforticons-0.1.0.dist-info/RECORD
