Metadata-Version: 2.1
Name: comforticons
Version: 0.1.0
Summary: ComfortIcons is an identicon generation module for different identicon/icon/gravatar/avatar flavors
Home-page: https://github.com/blackwarlow/comforticons
License: BSD-3-Clause
Keywords: identicon,avatar,gravatar
Author: blackwarlow
Requires-Python: >=3.8,<4.0
Classifier: License :: OSI Approved :: BSD License
Classifier: Programming Language :: Python :: 3
Classifier: Programming Language :: Python :: 3.8
Classifier: Programming Language :: Python :: 3.9
Classifier: Programming Language :: Python :: 3.10
Classifier: Programming Language :: Python :: 3.11
Requires-Dist: Pillow (>=9.5.0,<10.0.0)
Project-URL: Documentation, https://github.com/blackwarlow/comforticons
Project-URL: Repository, https://github.com/blackwarlow/comforticons
